cocotst/__main__.py
cocotst/app.py
cocotst/dispatcher.py
cocotst/entry.py
cocotst/services.py
cocotst/cli/__init__.py
cocotst/config/debug.py
cocotst/config/webserver.py
cocotst/event/__init__.py
cocotst/event/builtin.py
cocotst/event/message.py
cocotst/event/proactive.py
cocotst/event/robot.py
cocotst/message/element.py
cocotst/message/keyboard.py
cocotst/message/parser/base.py
cocotst/message/parser/msgsaw.py
cocotst/network/qqapi.py
cocotst/network/services.py
cocotst/network/sign.py
cocotst/network/types.py
cocotst/network/webhook.py
cocotst/network/model/http_api.py
cocotst/network/model/target.py
cocotst/network/model/webhook.py
cocotst/network/model/event_element/__init__.py
cocotst/network/model/event_element/guild.py
cocotst/network/model/event_element/normal.py
cocotst/utils/__init__.py
cocotst/utils/guild.py
cocotst/utils/request.py
cocotst/utils/debug/__init__.py
cocotst-0.1.2.dist-info/METADATA
cocotst-0.1.2.dist-info/WHEEL
cocotst-0.1.2.dist-info/licenses/LICENSE
cocotst-0.1.2.dist-info/RECORD
