Metadata-Version: 2.4
Name: Cocotst
Version: 0.1.2
Summary: Easily to code qqoffcial bot.
Author-email: Sibuxiangx <sibuxiang@proton.me>
License: MIT
License-File: LICENSE
Requires-Python: >=3.11
Requires-Dist: aiofiles>=24.1.0
Requires-Dist: cryptography>=43.0.3
Requires-Dist: fastapi>=0.115.4
Requires-Dist: graia-broadcast>=0.23.5
Requires-Dist: httpx>=0.28.1
Requires-Dist: launart>=0.8.2
Requires-Dist: loguru>=0.7.2
Requires-Dist: pydantic>=2.0
Requires-Dist: requests>=2.32.3
Requires-Dist: richuru>=0.1.1
Requires-Dist: typer>=0.13.1
Requires-Dist: uvicorn>=0.32.0
Requires-Dist: watchdog[watchmedo]>=6.0.0
Provides-Extra: alc
Requires-Dist: arclet-alconna-tools>=0.7.10; extra == 'alc'
Requires-Dist: arclet-alconna>=1.8.34; extra == 'alc'
Provides-Extra: dev
Requires-Dist: black>=24.10.0; extra == 'dev'
Requires-Dist: isort>=5.13.2; extra == 'dev'
Requires-Dist: pyright>=1.1.0; extra == 'dev'
Provides-Extra: docs
Requires-Dist: mkdocs-gen-files>=0.5.0; extra == 'docs'
Requires-Dist: mkdocs-literate-nav>=0.6.1; extra == 'docs'
Requires-Dist: mkdocs-material>=9.5.45; extra == 'docs'
Requires-Dist: mkdocs-section-index>=0.3.9; extra == 'docs'
Requires-Dist: mkdocstrings-python>=1.12.2; extra == 'docs'
Provides-Extra: voice
Requires-Dist: graiax-silkcoder[ffmpeg]>=0.3.6; extra == 'voice'
